itkwasm_elastix_wasi/__init__.py
itkwasm_elastix_wasi/_version.py
itkwasm_elastix_wasi/default_parameter_map.py
itkwasm_elastix_wasi/elastix.py
itkwasm_elastix_wasi/read_parameter_files.py
itkwasm_elastix_wasi/transformix.py
itkwasm_elastix_wasi/write_parameter_files.py
itkwasm_elastix_wasi/wasm_modules/default-parameter-map.wasi.wasm
itkwasm_elastix_wasi/wasm_modules/elastix.wasi.wasm
itkwasm_elastix_wasi/wasm_modules/read-parameter-file.wasi.wasm
itkwasm_elastix_wasi/wasm_modules/read-parameter-files.wasi.wasm
itkwasm_elastix_wasi/wasm_modules/transformix.wasi.wasm
itkwasm_elastix_wasi/wasm_modules/write-parameter-files.wasi.wasm
itkwasm_elastix_wasi-1.0.2.dist-info/METADATA
itkwasm_elastix_wasi-1.0.2.dist-info/WHEEL
itkwasm_elastix_wasi-1.0.2.dist-info/RECORD
