Metadata-Version: 2.4
Name: itkwasm-elastix-wasi
Version: 1.0.2
Dynamic: Summary
Project-URL: Home, https://github.com/InsightSoftwareConsortium/ITKElastix
Project-URL: Source, https://github.com/InsightSoftwareConsortium/ITKElastix
License-Expression: Apache-2.0
Keywords: itkwasm,wasi,webassembly
Classifier: Development Status :: 3 - Alpha
Classifier: Environment :: WebAssembly
Classifier: Environment :: WebAssembly :: Emscripten
Classifier: Environment :: WebAssembly :: WASI
Classifier: Intended Audience :: Developers
Classifier: Intended Audience :: Science/Research
Classifier: License :: OSI Approved :: Apache Software License
Classifier: Programming Language :: C++
Classifier: Programming Language :: Python
Classifier: Programming Language :: Python :: 3
Classifier: Programming Language :: Python :: 3.9
Classifier: Programming Language :: Python :: 3.10
Classifier: Programming Language :: Python :: 3.11
Classifier: Programming Language :: Python :: 3.12
Classifier: Programming Language :: Python :: 3.13
Requires-Python: >=3.9
Requires-Dist: importlib-resources
Requires-Dist: itkwasm>=1.0.b195
Provides-Extra: test
Requires-Dist: itkwasm-compare-images<6,>=5.2.0; extra == 'test'
Requires-Dist: itkwasm-image-io<2,>=1.2.1; extra == 'test'
Requires-Dist: pytest; extra == 'test'
